{"data": [{"title": "Q4 results may spark selective market rebound: Daljeet Kohli", "link": "https://economictimes.indiatimes.com/markets/expert-view/q4-results-may-spark-selective-market-rebound-daljeet-kohli/articleshow/128880855.cms", "snippet": "Daljeet Kohli advocates strict bottom-up investing amid volatile markets, favoring earnings-driven stock selection. He sees opportunities in CV autos and ancillaries, remains cautious on IT and microf", "source": "rss", "query": "general", "published_at": "Sat, 28 Feb 2026 15:05:13 +0530", "timestamp": "2026-02-28T18:56:03.986193", "relevance_score": 0.5800000000000001, "quality_score": 0.5800000000000001, "filtered_at": "2026-02-28T18:56:07.044519"}, {"title": "Tata Elxsi Q4 net profit, revenue decline QoQ; firm declares dividend of Rs 70 per share", "link": "https://www.moneycontrol.com/news/business/tata-elxsi-q4-net-profit-revenue-decline-qoq-firm-declares-dividendrs-70-per-share_17532061.html", "snippet": "<img align=\" left\" alt=\"Tata Elxsi Q4 net profit, revenue decline QoQ; firm declares dividend of Rs 70 per share\" border=\"0\" height=\"75\" hspace=\"5\" src=\"https://www.moneycontrol.com/news_image_files/2", "source": "rss", "query": "general", "published_at": "Tue, 23 Apr 2024 18:51:45 +0530", "timestamp": "2026-02-28T18:56:04.583501", "relevance_score": 0.5800000000000001, "quality_score": 0.5800000000000001, "filtered_at": "2026-02-28T18:56:07.044556"}, {"title": "Cyient DLM#39;s profit after tax in FY24 surges 93%", "link": "https://www.moneycontrol.com/news/business/cyient-dlm39s-profit-after-taxfy24-surges-93_17532091.html", "snippet": "<img align=\" left\" alt=\"Cyient DLM#39;s profit after tax in FY24 surges 93%\" border=\"0\" height=\"75\" hspace=\"5\" src=\"https://www.moneycontrol.com/news_image_files/2023/200x200/s/shutterstock_2170560599", "source": "rss", "query": "general", "published_at": "Tue, 23 Apr 2024 17:56:47 +0530", "timestamp": "2026-02-28T18:56:04.583515", "relevance_score": 0.56, "quality_score": 0.56, "filtered_at": "2026-02-28T18:56:07.044561"}, {"title": "Tata Consumer Q4 net profit falls 19% to Rs 217 cr, firm declares dividend of Rs 7.75 per share", "link": "https://www.moneycontrol.com/news/business/tata-consumer-q4-net-profit-falls-19-to-rs-217-cr-firm-declares-dividendrs-775-per-share_17532071.html", "snippet": "<img align=\" left\" alt=\"Tata Consumer Q4 net profit falls 19% to Rs 217 cr, firm declares dividend of Rs 7.75 per share\" border=\"0\" height=\"75\" hspace=\"5\" src=\"https://www.moneycontrol.com/news_image_", "source": "rss", "query": "general", "published_at": "Tue, 23 Apr 2024 16:27:47 +0530", "timestamp": "2026-02-28T18:56:04.583521", "relevance_score": 0.56, "quality_score": 0.56, "filtered_at": "2026-02-28T18:56:07.044565"}, {"title": "ICICI Pru Life Q4 net profit falls 26% to Rs 174 cr, insurer announces dividend", "link": "https://www.moneycontrol.com/news/business/icici-pru-life-q4-net-profit-falls-26-to-rs-174-cr-insurer-announces-dividend_17532101.html", "snippet": "<img align=\" left\" alt=\"ICICI Pru Life Q4 net profit falls 26% to Rs 174 cr, insurer announces dividend\" border=\"0\" height=\"75\" hspace=\"5\" src=\"https://www.moneycontrol.com/news_image_files/2023/200x2", "source": "rss", "query": "general", "published_at": "Tue, 23 Apr 2024 18:26:16 +0530", "timestamp": "2026-02-28T18:56:04.583508", "relevance_score": 0.51, "quality_score": 0.51, "filtered_at": "2026-02-28T18:56:07.044569"}, {"title": "LTIMindtree Q4 Preview: Lower pass-through revenue seen impacting growth marginally", "link": "https://www.moneycontrol.com/news/business/ltimindtree-q4-preview-lower-pass-through-revenue-seen-impacting-growth-marginally_17531881.html", "snippet": "<img align=\" left\" alt=\"LTIMindtree Q4 Preview: Lower pass-through revenue seen impacting growth marginally\" border=\"0\" height=\"75\" hspace=\"5\" src=\"https://www.moneycontrol.com/news_image_files/2023/2", "source": "rss", "query": "general", "published_at": "Tue, 23 Apr 2024 15:51:27 +0530", "timestamp": "2026-02-28T18:56:04.583540", "relevance_score": 0.5, "quality_score": 0.5, "filtered_at": "2026-02-28T18:56:07.044572"}, {"title": "Bitcoin hovers near $65,000 as risk-off sentiment wipes out midweek gains", "link": "https://economictimes.indiatimes.com/markets/cryptocurrency/bitcoin-hovers-near-65000-as-risk-off-sentiment-wipes-out-midweek-gains/articleshow/128878689.cms", "snippet": "Bitcoin hovers around $65,000 amid broad crypto declines, with Ethereum and major altcoins down. Market shows tactical stability but structural fragility persists, while global financial risks and AI ", "source": "rss", "query": "general", "published_at": "Sat, 28 Feb 2026 13:30:14 +0530", "timestamp": "2026-02-28T18:56:03.986220", "relevance_score": 0.48, "quality_score": 0.48, "filtered_at": "2026-02-28T18:56:07.044576"}, {"title": "Air India enters into codeshare pact with Japan#39;s All Nippon Airways", "link": "https://www.moneycontrol.com/news/business/air-india-enters-into-codeshare-pactjapan39s-all-nippon-airways_17531801.html", "snippet": "<img align=\" left\" alt=\"Air India enters into codeshare pact with Japan#39;s All Nippon Airways\" border=\"0\" height=\"75\" hspace=\"5\" src=\"https://www.moneycontrol.com/news_image_files/2024/200x200/B/BOE", "source": "rss", "query": "general", "published_at": "Tue, 23 Apr 2024 14:44:20 +0530", "timestamp": "2026-02-28T18:56:04.583554", "relevance_score": 0.48, "quality_score": 0.48, "filtered_at": "2026-02-28T18:56:07.044579"}, {"title": "Iran-Israel war: Up 20% in 2026, crude oil stares at $80 a barrel", "link": "https://economictimes.indiatimes.com/markets/commodities/news/iran-israel-war-up-20-in-2026-crude-oil-stares-at-80-a-barrel/articleshow/128884731.cms", "snippet": "Oil prices rallied sharply after US and Israeli strikes on Iran heightened Middle East tensions. Brent and WTI hit multi-month highs, with further gains likely amid supply risks through the Strait of ", "source": "rss", "query": "general", "published_at": "Sat, 28 Feb 2026 17:21:13 +0530", "timestamp": "2026-02-28T18:56:03.986156", "relevance_score": 0.43000000000000005, "quality_score": 0.43000000000000005, "filtered_at": "2026-02-28T18:56:07.044582"}, {"title": "LT manufactures hydrotreating reactor for refinery in Mexico", "link": "https://www.moneycontrol.com/news/business/lt-manufactures-hydrotreating-reactor-for-refinerymexico_17531811.html", "snippet": "<img align=\" left\" alt=\"LT manufactures hydrotreating reactor for refinery in Mexico\" border=\"0\" height=\"75\" hspace=\"5\" src=\"https://www.moneycontrol.com/news_image_files/2023/200x200/L/Larsen-Toubro_", "source": "rss", "query": "general", "published_at": "Tue, 23 Apr 2024 14:47:18 +0530", "timestamp": "2026-02-28T18:56:04.583548", "relevance_score": 0.43000000000000005, "quality_score": 0.43000000000000005, "filtered_at": "2026-02-28T18:56:07.044585"}, {"title": "ICICI Prudential Life Insurance to focus on growing absolute VNB amid slump in FY24", "link": "https://www.moneycontrol.com/news/business/icici-prudential-life-insurance-to-focusgrowing-absolute-vnb-amid-slumpfy24_17532041.html", "snippet": "<img align=\" left\" alt=\"ICICI Prudential Life Insurance to focus on growing absolute VNB amid slump in FY24\" border=\"0\" height=\"75\" hspace=\"5\" src=\"https://www.moneycontrol.com/news_image_files/2023/2", "source": "rss", "query": "general", "published_at": "Tue, 23 Apr 2024 22:36:32 +0530", "timestamp": "2026-02-28T18:56:04.583480", "relevance_score": 0.4, "quality_score": 0.4, "filtered_at": "2026-02-28T18:56:07.044588"}, {"title": "Hindustan Unilever Q4 Preview: Price cuts, slow demand, regional competition to hurt topline", "link": "https://www.moneycontrol.com/news/business/hindustan-unilever-q4-preview-price-cuts-slow-demand-regional-competition-to-hurt-topline_17531901.html", "snippet": "<img align=\" left\" alt=\"Hindustan Unilever Q4 Preview: Price cuts, slow demand, regional competition to hurt topline\" border=\"0\" height=\"75\" hspace=\"5\" src=\"https://www.moneycontrol.com/news_image_fil", "source": "rss", "query": "general", "published_at": "Tue, 23 Apr 2024 16:05:45 +0530", "timestamp": "2026-02-28T18:56:04.583534", "relevance_score": 0.4, "quality_score": 0.4, "filtered_at": "2026-02-28T18:56:07.044591"}, {"title": "Bitcoin falls below $65,000: What\u2019s driving the latest crypto crash?", "link": "https://www.livemint.com/market/cryptocurrency/bitcoin-falls-below-65-000-what-s-driving-the-latest-crypto-crash-11772281266986.html", "snippet": "Bitcoin prices fell below $65,000 on Saturday due to military actions by Israel and the US against Iran. Details here.", "source": "rss", "query": "general", "published_at": "Sat, 28 Feb 2026 18:07:03 +0530", "timestamp": "2026-02-28T18:56:04.918424", "relevance_score": 0.4, "quality_score": 0.4, "filtered_at": "2026-02-28T18:56:07.044594"}, {"title": "Israel, France, Germany to EU: What India's defence diplomacy means for China, Pakistan, US and NATO?", "link": "https://www.livemint.com/market/stock-market-news/israel-france-germany-to-eu-what-indias-defence-diplomacy-means-for-china-pakistan-and-nato-11772247388504.html", "snippet": "India's recent defence deals with Germany, the EU, France, and Israel enhance its military capabilities and technology transfer, aiming for self-reliance", "source": "rss", "query": "general", "published_at": "Sat, 28 Feb 2026 08:48:58 +0530", "timestamp": "2026-02-28T18:56:04.918501", "relevance_score": 0.4, "quality_score": 0.4, "filtered_at": "2026-02-28T18:56:07.044597"}, {"title": "Adani Group To Manufacture India's Longest 91.2-Metre Wind Turbine Blade", "link": "https://www.ndtvprofit.com/business/adani-group-to-manufacture-india-s-longest-91-2-metre-wind-turbine-blade-11149712#publisher=newsstand", "snippet": "A truck transports materials at the Adani Green Energy Ltd. renewable energy park in Khavda, Gujarat.", "source": "rss", "query": "general", "published_at": "Sat, 28 Feb 2026 18:23:45 +0530", "timestamp": "2026-02-28T18:56:06.897975", "relevance_score": 0.4, "quality_score": 0.4, "filtered_at": "2026-02-28T18:56:07.044600"}, {"title": "Israel-Iran War News Live Updates: Iran Reports 24 Killled, 60 Injured, Elementary School Sees 40 Casualties From US-Israel Strike", "link": "https://www.ndtvprofit.com/world/israel-iran-war-news-live-updates-multiple-explosions-in-tehran-israel-state-of-emergency-trump-netanyahu-khamenei-11148429#publisher=newsstand", "snippet": "People watch as smoke rises on the skyline after an explosion in Tehran, Iran.", "source": "rss", "query": "general", "published_at": "Sat, 28 Feb 2026 18:07:40 +0530", "timestamp": "2026-02-28T18:56:06.897989", "relevance_score": 0.4, "quality_score": 0.4, "filtered_at": "2026-02-28T18:56:07.044603"}, {"title": "Nifty 50 may hit 15K by the end of 2027. Experts bet high on this asset", "link": "https://www.livemint.com/market/stock-market-news/stock-market-crash-nifty-50-may-hit-15-000-by-end-of-2027-experts-suggest-this-asset-to-park-money-11772258877408.html", "snippet": "Stock market crash: Experts are highly bearish on Indian stock market on India's household debt reaching 70% of GDP, and earnings per share nosediving by around 50%", "source": "rss", "query": "general", "published_at": "Sat, 28 Feb 2026 12:08:30 +0530", "timestamp": "2026-02-28T18:56:04.918493", "relevance_score": 0.26, "quality_score": 0.26, "filtered_at": "2026-02-28T18:56:07.044606"}, {"title": "Bottom-up stock opportunities emerge as markets consolidate post-correction: Sudip Bandyopadhyay", "link": "https://economictimes.indiatimes.com/markets/expert-view/bottom-up-stock-opportunities-emerge-as-markets-consolidate-post-correction-sudip-bandyopadhyay/articleshow/128878818.cms", "snippet": "Sudip Bandyopadhyay highlights selective bottom-up investment opportunities in chemicals, defense, energy, retail, and telecom sectors amid market consolidation and improving corporate fundamentals. F", "source": "rss", "query": "general", "published_at": "Sat, 28 Feb 2026 13:46:14 +0530", "timestamp": "2026-02-28T18:56:03.986215", "relevance_score": 0.23, "quality_score": 0.23, "filtered_at": "2026-02-28T18:56:07.044609"}, {"title": "FIIs pour Rs 22,615 crore into Indian equities in February. Can Iran-Israel conflict flip the trend?", "link": "https://economictimes.indiatimes.com/markets/stocks/news/fiis-pour-rs-22615-crore-into-indian-equities-in-february-can-iran-israel-conflict-flip-the-trend/articleshow/128885382.cms", "snippet": "Foreign investors showed buying interest in Indian stocks in February. However, recent geopolitical tensions are causing concern. Experts believe FIIs may pause fresh investments. They are likely to o", "source": "rss", "query": "general", "published_at": "Sat, 28 Feb 2026 17:50:47 +0530", "timestamp": "2026-02-28T18:56:03.986131", "relevance_score": 0.21000000000000002, "quality_score": 0.21000000000000002, "filtered_at": "2026-02-28T18:56:07.044613"}, {"title": "FPIs turn net buyers in Indian stock market; February inflows top  \u20b922,600 crore, highest in 16 months", "link": "https://www.livemint.com/market/stock-market-news/fpis-turn-net-buyers-in-indian-stock-market-february-inflows-top-rs-22-600-crore-highest-in-16-months-11772272448552.html", "snippet": "FPIs net bought Indian equities worth  \u20b922,615 crore in February, according to data from National Securities Depository Limited (NSDL). Previously, FPIs had invested  \u20b957,724 crore in September 2024.", "source": "rss", "query": "general", "published_at": "Sat, 28 Feb 2026 15:39:45 +0530", "timestamp": "2026-02-28T18:56:04.918464", "relevance_score": 0.21000000000000002, "quality_score": 0.21000000000000002, "filtered_at": "2026-02-28T18:56:07.044616"}, {"title": "Stock market holidays in March 2026: NSE, BSE to remain closed on these days next month", "link": "https://www.livemint.com/market/stock-market-news/stock-market-holidays-in-march-2026-nse-bse-to-remain-closed-on-these-days-next-month-11772272908550.html", "snippet": "Stock market holidays in March 2026: Those confused about the trade holiday date on Holi should scan the list of trade holidays available on the BSE and the NSE websites", "source": "rss", "query": "general", "published_at": "Sat, 28 Feb 2026 15:44:43 +0530", "timestamp": "2026-02-28T18:56:04.918455", "relevance_score": 0.2, "quality_score": 0.2, "filtered_at": "2026-02-28T18:56:07.044619"}], "expiry": "2026-02-28T19:26:07.047004"}